cipher_craftt/__init__.py
cipher_craftt/breach_checker.py
cipher_craftt/cli.py
cipher_craftt/context_aware_generator.py
cipher_craftt/entropy_calculator.py
cipher_craftt/generate_mnemonic_password.py
cipher_craftt/generator.py
cipher_craftt/obfuscator.py
cipher_craftt/passphrase_generator.py
cipher_craftt/password_history.py
cipher_craftt/password_policy.py
cipher_craftt/pronunciation_guide.py
cipher_craftt/secure_sharing.py
cipher_craftt/strength_checker.py
cipher_craftt/totp.py
cipher_craftt/wordlist/languages/ar.txt
cipher_craftt/wordlist/languages/cs.txt
cipher_craftt/wordlist/languages/da.txt
cipher_craftt/wordlist/languages/de.txt
cipher_craftt/wordlist/languages/en.txt
cipher_craftt/wordlist/languages/es.txt
cipher_craftt/wordlist/languages/fr.txt
cipher_craftt/wordlist/languages/he.txt
cipher_craftt/wordlist/languages/hr.txt
cipher_craftt/wordlist/languages/it.txt
cipher_craftt/wordlist/languages/ka.txt
cipher_craftt/wordlist/languages/nl.txt
cipher_craftt/wordlist/languages/no.txt
cipher_craftt/wordlist/languages/pl.txt
cipher_craftt/wordlist/languages/pt.txt
cipher_craftt/wordlist/languages/ru.txt
cipher_craftt/wordlist/languages/sr.txt
cipher_craftt/wordlist/languages/sv.txt
cipher_craftt/wordlist/languages/tr.txt
cipher_craftt/wordlist/languages/uk.txt
cipher_craftt-0.1.18.dist-info/LICENSE
cipher_craftt-0.1.18.dist-info/METADATA
cipher_craftt-0.1.18.dist-info/WHEEL
cipher_craftt-0.1.18.dist-info/entry_points.txt
cipher_craftt-0.1.18.dist-info/top_level.txt
cipher_craftt-0.1.18.dist-info/RECORD
