Metadata-Version: 2.1
Name: cipher-craftt
Version: 0.1.18
Summary: A comprehensive tool for password management including generation, strength checking, expiry tracking, and secure sharing.
Home-page: https://github.com/jarvismayur/ciphercraft
Author: Mayur Tembhare
Author-email: tembharemayur@gmail.com
Classifier: Development Status :: 3 - Alpha
Classifier: Intended Audience :: Developers
Classifier: License :: OSI Approved :: Apache Software License
Classifier: Programming Language :: Python :: 3
Classifier: Programming Language :: Python :: 3.8
Classifier: Programming Language :: Python :: 3.9
Classifier: Programming Language :: Python :: 3.10
Classifier: Programming Language :: Python :: 3.11
Classifier: Programming Language :: Python :: 3.12
Classifier: Operating System :: OS Independent
Requires-Python: >=3.6
License-File: LICENSE
Requires-Dist: cryptography
